house/__init__.py
us_house-0.0a1.dev1.dist-info/LICENSE
us_house-0.0a1.dev1.dist-info/METADATA
us_house-0.0a1.dev1.dist-info/WHEEL
us_house-0.0a1.dev1.dist-info/top_level.txt
us_house-0.0a1.dev1.dist-info/RECORD
